meters/__init__.py
meters/printing.py
meters/resources.py
code_meters-0.0.3.dist-info/LICENSE
code_meters-0.0.3.dist-info/METADATA
code_meters-0.0.3.dist-info/WHEEL
code_meters-0.0.3.dist-info/top_level.txt
code_meters-0.0.3.dist-info/RECORD
